nf_validator/__init__.py
nf_validator/main.py
nf_validator-1.1.0.dist-info/METADATA
nf_validator-1.1.0.dist-info/WHEEL
nf_validator-1.1.0.dist-info/top_level.txt
nf_validator-1.1.0.dist-info/RECORD
