Metadata-Version: 2.1
Name: nf-validator
Version: 1.1.0
Summary: A package for validating name and surname
Home-page: https://github.com/sosthene14/NF_validating/
Author: Sosthène Mounsamboté
Author-email: sosthenemounsambote14@gmail.com
Classifier: Programming Language :: Python :: 3
Classifier: License :: OSI Approved :: MIT License
Classifier: Operating System :: OS Independent
Requires-Python: >=3.6
Requires-Dist: unicodedata2
